Todoska/Database.py
Todoska/__main__.py
Todoska/models.py
Todoska-0.2.7.dist-info/DESCRIPTION.rst
Todoska-0.2.7.dist-info/METADATA
Todoska-0.2.7.dist-info/RECORD
Todoska-0.2.7.dist-info/WHEEL
Todoska-0.2.7.dist-info/entry_points.txt
Todoska-0.2.7.dist-info/metadata.json
Todoska-0.2.7.dist-info/top_level.txt
