Metadata-Version: 2.0
Name: Todoska
Version: 0.2.7
Summary: A Basic Todo Tracker in Cli
Home-page: https://github.com/Abbhiishek/Todoska
Author: Abhishek Kushwaha
Author-email: abhishekkushwaha1479@gmail.com
License: MIT
Keywords: Python,cli,Todo,Todotracker,todo-tracker,todo-tracker-cli,Todoska
Platform: UNKNOWN
Classifier: Development Status :: 5 - Production/Stable
Classifier: Intended Audience :: Education
Classifier: Operating System :: Microsoft :: Windows :: Windows 10
Classifier: License :: OSI Approved :: MIT License
Classifier: Programming Language :: Python :: 3
Requires-Python: >=3.6
Requires-Dist: typer
Requires-Dist: rich
